pysqlx_engine/__init__.py
pysqlx_engine/_core/abc/base_pool.py
pysqlx_engine/_core/abc/conn.py
pysqlx_engine/_core/abc/workers.py
pysqlx_engine/_core/aconn.py
pysqlx_engine/_core/aconn.pyi
pysqlx_engine/_core/apool.py
pysqlx_engine/_core/conn.py
pysqlx_engine/_core/conn.pyi
pysqlx_engine/_core/const.py
pysqlx_engine/_core/errors.py
pysqlx_engine/_core/helper.py
pysqlx_engine/_core/json_econder.py
pysqlx_engine/_core/logger.py
pysqlx_engine/_core/param.py
pysqlx_engine/_core/param_converter.py
pysqlx_engine/_core/parser.py
pysqlx_engine/_core/pool.py
pysqlx_engine/_core/util.py
pysqlx_engine/errors.py
pysqlx_engine/py.typed
pysqlx_engine-0.3.2.dist-info/METADATA
pysqlx_engine-0.3.2.dist-info/WHEEL
pysqlx_engine-0.3.2.dist-info/RECORD
