Metadata-Version: 2.1
Name: pysqlx-engine
Version: 0.3.2
Summary: Async and Sync SQL Engine for Python, with support for PostgreSQL, MySQL, SQLite and Microsoft SQL Server.
Home-page: https://carlos-rian.github.io/pysqlx-engine
License: MIT
Keywords: async,database,sql,engine,fastapi
Author: Carlos Rian
Author-email: crian.rian@gmail.com
Requires-Python: >=3.8,<4.0
Classifier: Development Status :: 4 - Beta
Classifier: Framework :: AnyIO
Classifier: Framework :: AsyncIO
Classifier: Framework :: FastAPI
Classifier: Framework :: IPython
Classifier: Framework :: Jupyter
Classifier: Intended Audience :: Developers
Classifier: Intended Audience :: Information Technology
Classifier: Intended Audience :: System Administrators
Classifier: License :: OSI Approved :: MIT License
Classifier: Operating System :: MacOS
Classifier: Operating System :: Microsoft
Classifier: Operating System :: OS Independent
Classifier: Operating System :: POSIX :: Linux
Classifier: Programming Language :: Python
Classifier: Programming Language :: Python :: 3
Classifier: Programming Language :: Python :: 3.8
Classifier: Programming Language :: Python :: 3.9
Classifier: Programming Language :: Python :: 3.10
Classifier: Programming Language :: Python :: 3.11
Classifier: Programming Language :: Python :: 3.12
Classifier: Programming Language :: Python :: 3.13
Classifier: Programming Language :: Python :: 3 :: Only
Classifier: Topic :: Database
Classifier: Topic :: Internet
Classifier: Topic :: Software Development
Classifier: Topic :: Software Development :: Libraries
Classifier: Topic :: Software Development :: Libraries :: Application Frameworks
Classifier: Topic :: Software Development :: Libraries :: Python Modules
Classifier: Typing :: Typed
Requires-Dist: Pygments (>=2.15.1,<3.0.0)
Requires-Dist: pydantic (>=1,<3) ; python_version >= "3.8"
Requires-Dist: pysqlx-core (>=0.2.3,<0.3.0)
Project-URL: Documentation, https://carlos-rian.github.io/pysqlx-engine
Project-URL: Repository, https://github.com/carlos-rian/pysqlx-engine
